elevador.v

module FSMpiso(input wire[3:0] piso,input wire puerta, accion, llego, clk,reset, output reg [2:0] estado,output wire [3:0] next);
    /*  piso: indica a los pisos a los cuales las personas quieren ir, ya sea por peticion para subir, o si se  
              se seleccionaron los pisos internamente en el elevador.
        accion: indica la accion anterior que se estaba realizando, 1 si se estaba subiendo, 0 si se estaba bajando
        Puerta: indica si la puerta esta abierta (1) o cerrada (0)
        llego : indica si ya se llego al siguiente piso*/
    wire [2:0] nextEstado;
    //------------ bit 2 del nuevo estado ---------------------------------
    wire sn21,sn22,sn23, sn24,sn25 , sn26;
    //s1' s0'  + s2 Llegó' + s2 s1 s0 Acción
    assign sn21 = (~estado[1] & ~estado[0]) | (estado[2] & ~llego) | (estado[2] & estado[1] & estado[0] & accion);
    // s2' s0' PE2 PE1' Puerta'  + s2' s1' PE2 PE0' Puerta'
    assign sn22 = (~estado[2] & ~estado[0] & piso[2] & ~piso[1] & ~puerta) | (~estado[2] & ~estado[1] & piso[2] & ~piso[0] & ~puerta);
    //s2' s1 s0 PE2' PE0 Puerta'  
    assign sn23 = ~estado[2] & estado[1]& estado[0]& ~piso[2] & piso[0] & ~puerta;
    //s2' s1 PE2' PE1' PE0 Puerta'
    assign sn24 = ~estado[2] & estado[1] & ~piso[2] & ~piso[1] & piso[0] & ~puerta; 
    // s2' s0 PE2' PE1 PE0' Puerta'  
    assign  sn25 = ~estado[2] & estado[0] & ~piso[2] & piso[1] & ~piso[0] & ~puerta;
    //s2' PE3 PE2' PE1' PE0' Puerta' ;
    assign sn26 = ~estado[2] & piso[3] & ~piso[2] & ~piso[1] & ~piso[0] & ~puerta;

    assign nextEstado[2] = sn21 | sn22 | sn23 | sn24 | sn25 | sn26;

    // ---------------------------- bit 1 del nuevo estado----------------------------
    wire sn11, sn12 , sn13, sn14, sn15,sn16, sn17;
    // s2' s1 s0  + s0' PE3' PE1 Puerta'   
    assign sn11 = (~estado[2] & estado[1] & estado[0]) | (~estado[0] & ~piso[3] & piso[1] & ~puerta) ;
    //s2 s1' s0 Acción Llegó + s1 s0' PE1 
    assign sn12 = (estado[2] & ~estado[1] & estado[0] & accion & llego) | (estado[1] & ~estado[0] & piso[1]);
    // s1 s0' PE0'  + s1 s0' Puerta  + s2 s1 Acción'
    assign sn13 = (estado[1] & ~estado[0] & ~piso[0]) | (estado[1] & ~estado[0] & puerta) | (estado[2] & estado[1]& ~accion);
    //s1 s0 Llegó' + s1 s0' PE3 Acción
    assign sn14 = (estado[1] & estado[0] & ~llego) | (estado[1] & ~estado[0] & piso[3] & accion );
    //s1' s0' PE3' PE2 Puerta'
    assign sn15 = ~estado[1] & ~estado[0] & ~piso[3] & piso[2] & ~puerta ;
    //s2 s0' PE3' PE0 Puerta'
    assign  sn16 = estado[2] & ~estado[0] & ~piso[3] & piso[0] & ~puerta;
    // s0' PE3' PE2 Puerta' Acción ;
    assign sn17 = ~estado[0] & ~piso[3] & piso[2] & ~puerta & accion;


    assign nextEstado[1] = sn11 | sn12 | sn13 | sn14 | sn15 | sn16 |sn17 ;

    //-------------------------- bit 0 del nuevo estado ------------------------------
    wire sn01, sn02, sn03, sn04, sn05,sn06, sn07, sn08,sn09;
    //s2' s1'  + s2' s0 PE2  + s2' s0 Puerta
    assign sn01 = (~estado[2] & ~estado[1]) | (~estado[2] & estado[0] & piso[2]) | (~estado[2] & estado[0] & puerta);
    // s2 s0 Acción'  + s2 s0 Llegó'
    assign sn02 = (estado[2] & estado[0] & ~accion) | (estado[2] & estado[0] & ~llego);
    //  s2' s0 PE1' PE0'  + s2' s0 PE3 Acción
    assign sn03 = (~estado[2] & estado[0] & ~piso[1] & ~piso[0]) | (~estado[2] & estado[0] & piso[3] & accion);
    // s2 s1 s0' Acción Llegó
    assign sn04 = estado[2] & estado[1] & ~estado[0] & accion & llego;
    // s2' s0' PE1' PE0 Puerta' Acción'
    assign sn05 = ~estado[2] & ~estado[0] & ~piso[1] & piso[0] & ~puerta  & ~accion;
    // s2' s0' PE3' PE2' PE1' PE0 Puerta'
    assign sn06 = ~estado[2] & ~estado[0] & ~piso[3] & ~piso[2] & ~piso[1] & piso[0] & ~puerta;
    // s1' s0' PE3' PE2 Puerta'
    assign  sn07 = ~estado[1] & ~estado[0] & ~piso[3] & piso[2] & ~puerta;
    // s1' s0' PE3' PE1 Puerta'  
    assign sn08 = ~estado[1] & ~estado[0] & ~piso[3] & piso[1] & ~puerta;
    //s1' s0' PE3' PE0 Puerta' ;
    assign sn09 = ~estado[1] & ~estado[0] & ~piso[3] & piso[0] & ~puerta;

    assign nextEstado[0] = sn01 | sn02 | sn03 | sn04 | sn05 | sn06 | sn07 | sn08 | sn09;
    // -------- bit 3 de la salida ------------
    wire y31, y32;
    //s2' s1 s0 PE3 PE2' Puerta' Acción
    assign y31 = ~estado[2] & estado[1] & estado[0] & piso[3] & ~piso[2] & ~puerta & accion;
    //s2' s1 s0 PE3 PE2' PE1' PE0' Puerta' ;
    assign y32 = ~estado[2] & estado[1] & estado[0] & piso[3] & ~piso[2] & ~piso[1] & ~piso[0] & ~puerta;

    assign next[3] = y31 | y32;
    // --------- bit 2 de la salida ------------
    wire y21,y22,y23,y24,y25,y26,y27; 
    //s1' s0' PE3' PE2 Puerta'
    assign y21 = ~estado[1] & ~estado[0] & ~piso[3] & piso[2] & ~puerta;
    //s1' s0' PE3' PE1 Puerta'
    assign y22 = ~estado[1] & ~estado[0] & ~piso[3] & piso[1] & ~puerta;
    //s1' s0' PE3' PE0 Puerta'
    assign y23 = ~estado[1] & ~estado[0] & ~piso[3] & piso[0] & ~puerta;
    //s2' s0' PE3 PE1' PE0' Puerta' 
    assign y24 = ~estado[2] & ~estado[0] & piso[3] & ~piso[1] & ~piso[0] & ~puerta;
    // s2' s0' PE2 PE1' PE0' Puerta'
    assign y25 = ~estado[2] & ~estado[0] & piso[2] & ~piso[1] & ~piso[0] & ~puerta;
    // s2' s0' PE3 PE1' Puerta' Acción
    assign y26= ~estado[2] & ~estado[0] & piso[3] & ~piso[1] & ~puerta &accion;
    // s2' s0' PE2 PE1' Puerta' Acción
    assign y27 = ~estado[2] &  ~estado[0] & piso[2] & ~piso[1] & ~puerta & accion;

    assign next[2] = y21 | y22 | y23| y24 | y25| y26| y27 ; 
    // --------- bit 1 de la salida ------------------------
    wire y11,y12,y13,y14,y15,y16;
    //s2' s1' PE3 PE0' Puerta'
    assign y11 = ~estado[2] & ~estado[1] & piso[3] & ~piso[0] & ~puerta;
    //s2' s1' PE2 PE0' Puerta'
    assign y12 = ~estado[2] & ~estado[1] & piso[2] & ~piso[0] & ~puerta;
    //s2' s1 s0 PE3' PE2' PE0 Puerta'
    assign y13 = ~estado[2] & estado[1] & estado[0] & ~piso[3] & ~piso[2] & piso[0] & ~puerta;
    //s2' s1 s0 PE2' PE0 Puerta' Acción'  
    assign y14 = ~estado[2] & estado[1] & estado[0] & ~piso[2] & piso[0] & ~puerta & ~accion; 
    //s2' s0 PE3' PE2' PE1 PE0' Puerta'
    assign y15 = ~estado[2] & estado[0] & ~piso[3] & ~piso[2] & piso[1] & ~piso[0] & ~puerta;
    //s2' s0 PE2' PE1 PE0' Puerta' Acción' 
    assign y16 = ~estado[2] & estado[0] & ~piso[2] & piso[1] & ~piso[0] & ~puerta & ~accion;


     assign next[1] = y11 |y12 | y13|y14|y15|y16;
    //------ bit 0 de la salida ---------------------------------------
    wire y01,y02;
    //y0 = s2' s0' PE1' PE0 Puerta' Acción'  + s2' s0' PE3' PE2' PE1' PE0 Puerta' ;
    assign y01 = ~estado[2] & ~estado[0] & ~piso[1] & piso[0] & ~puerta & ~accion;
    assign y02 = ~estado[2] & ~estado[0] & ~piso[3] & ~piso[2] & ~piso[1] & piso[0] & ~puerta;

     assign next[0] = y01 | y02;
    
    
    always @(posedge clk,posedge reset ) estado <=  (reset ? 3'b001 : nextEstado) ; //se asigna a estado el siguiente estado

endmodule

module Comparador(input wire[3:0] A, B, output wire igual, mayor, menor); //compara si 2 numeos de 4 bis son iguales mayores o menores
    assign igual = (A == B);
    assign  mayor = (A>B);
    assign  menor = (A<B);

endmodule

module FsmElevador(input wire emergencia, igual, menor, mayor,clk, rst ,output reg [1:0] estado, accion  );

    wire [1:0] nextEstado;
    //S1 = SN0' E' I' Ma' Me + SN1 E' I' Me;
    assign  nextEstado[1] = (~estado[0] & ~emergencia & ~igual & ~mayor & menor ) | (estado[1] & ~emergencia & ~igual & menor) ;
    //S0 = SN1' E' I' Ma ;
    assign  nextEstado[0] = ~estado[1] & ~emergencia & ~igual & mayor;

     

    always @ (posedge clk, posedge rst) begin
        estado = (rst ? 2'b00  : nextEstado );
        accion <= estado; 
    end 

endmodule

module FsmPuerta(input wire llego, emergencia, necesario,hecho, persona,abrir, piso,output [1:0] estado, output y );


endmodule

elevador_tb.v

module tb();
    reg[3:0] piso;
    reg puerta, accion, llego, clk, rst;
    wire [2:0] estado;
    wire [3:0] siguiente;

    FSMpiso fsm(piso,puerta,accion, llego, clk, rst,estado,siguiente);

    initial clk = 0;

    initial begin
        #1 rst= 0; accion = 0; llego = 0; puerta = 0; piso = 4'b000;
        #1 rst =1; 
        #1 rst = 0;
        #4 puerta = 1;
        #4 piso = 4'b0100;
        #4 puerta=0 ;piso = 4'b1100;accion = 1;
        #4 piso = 4'b0110;
        #4 llego = 1;
        #4 puerta = 1; piso=4'b0110; 
        #4 puerta = 0;
        #4 piso = 4'b0100; llego =0;
        #8 llego = 0;
        #4 llego =1; 
        #4 puerta = 1;
        #4 piso = 4'b1000;
        #4 puerta = 0; llego = 0;
        #8 llego = 1;

        #5 $finish;
    end


    always #2 clk = ~clk;

    initial begin
        $dumpfile("elevador_tb.vcd");
        $dumpvars(0,tb);
    end
 

endmodule

elevador_tb.vcd
$date
	Thu Oct 08 15:46:37 2020
$end
$version
	Icarus Verilog
$end
$timescale
	1ps
$end
$scope module tb $end
$var wire 4 ! siguiente [3:0] $end
$var wire 3 " estado [2:0] $end
$var reg 1 # accion $end
$var reg 1 $ clk $end
$var reg 1 % llego $end
$var reg 4 & piso [3:0] $end
$var reg 1 ' puerta $end
$var reg 1 ( rst $end
$scope module fsm $end
$var wire 1 # accion $end
$var wire 1 $ clk $end
$var wire 1 % llego $end
$var wire 4 ) piso [3:0] $end
$var wire 1 ' puerta $end
$var wire 1 ( reset $end
$var wire 1 * sn01 $end
$var wire 1 + sn02 $end
$var wire 1 , sn03 $end
$var wire 1 - sn04 $end
$var wire 1 . sn05 $end
$var wire 1 / sn06 $end
$var wire 1 0 sn07 $end
$var wire 1 1 sn08 $end
$var wire 1 2 sn09 $end
$var wire 1 3 sn11 $end
$var wire 1 4 sn12 $end
$var wire 1 5 sn13 $end
$var wire 1 6 sn14 $end
$var wire 1 7 sn15 $end
$var wire 1 8 sn16 $end
$var wire 1 9 sn17 $end
$var wire 1 : sn21 $end
$var wire 1 ; sn22 $end
$var wire 1 < sn23 $end
$var wire 1 = sn24 $end
$var wire 1 > sn25 $end
$var wire 1 ? sn26 $end
$var wire 1 @ y01 $end
$var wire 1 A y02 $end
$var wire 1 B y11 $end
$var wire 1 C y12 $end
$var wire 1 D y13 $end
$var wire 1 E y14 $end
$var wire 1 F y15 $end
$var wire 1 G y16 $end
$var wire 1 H y21 $end
$var wire 1 I y22 $end
$var wire 1 J y23 $end
$var wire 1 K y24 $end
$var wire 1 L y25 $end
$var wire 1 M y26 $end
$var wire 1 N y27 $end
$var wire 1 O y31 $end
$var wire 1 P y32 $end
$var wire 3 Q nextEstado [2:0] $end
$var wire 4 R next [3:0] $end
$var reg 3 S estado [2:0] $end
$upscope $end
$upscope $end
$enddefinitions $end
#0
$dumpvars
bx S
bx R
bx Q
xP
xO
xN
xM
xL
xK
xJ
xI
xH
xG
xF
xE
xD
xC
xB
xA
x@
x?
x>
x=
x<
x;
x:
x9
x8
x7
x6
x5
x4
x3
x2
x1
x0
x/
x.
x-
x,
x+
x*
bx )
x(
x'
bx &
x%
0$
x#
bx "
bx !
$end
#1
0?
0P
0;
0K
0L
0G
b0 !
b0 R
0>
0.
0B
0C
0E
0F
0@
0<
0=
04
07
08
0/
00
01
02
0H
0I
0J
0D
0A
0-
09
0O
0M
0N
b0 &
b0 )
0'
0%
0#
0(
#2
b1 Q
1,
0:
05
1*
03
06
0+
b1 "
b1 S
1(
1$
#3
0(
#4
0$
#6
1$
#7
1'
#8
0$
#10
1$
#11
b100 &
b100 )
#12
0$
#14
1$
#15
b101 Q
b10 !
b10 R
1B
1;
1C
1#
b1100 &
b1100 )
0'
#16
0$
#18
b0 !
b0 R
0;
0,
0B
0C
0*
1:
1+
b101 "
b101 S
1$
#19
b110 &
b110 )
#20
0$
#22
1$
#23
b10 Q
0:
0+
14
1%
#24
0$
#26
13
19
15
b10 "
b10 S
1$
#27
03
09
1'
#28
0$
#30
1$
#31
13
19
0'
#32
0$
#34
1$
#35
b110 Q
b100 !
b100 R
1;
1L
1N
03
04
0%
b100 &
b100 )
#36
0$
#38
b0 !
b0 R
0;
0L
0N
1:
b110 "
b110 S
1$
#40
0$
#42
1$
#44
0$
#46
1$
#47
b11 Q
0:
1-
1%
#48
0$
#50
b11 Q
05
09
1*
1,
13
0-
0:
b11 "
b11 S
1$
#51
1'
#52
0$
#54
1$
#55
b1000 &
b1000 )
#56
0$
#58
1$
#59
16
b111 Q
1O
b1000 !
b1000 R
1?
0*
1P
0%
0'
#60
0$
#62
b0 !
b0 R
0P
b111 Q
0O
0?
0,
03
1:
1+
b111 "
b111 S
1$
#64
0$
#66
1$
#67
b100 Q
06
0+
1%
#68
0$
#70
b100 Q
1:
b100 "
b100 S
1$
